Lindex/__init__.py
Lindex-1.1.1.dist-info/LICENSE
Lindex-1.1.1.dist-info/METADATA
Lindex-1.1.1.dist-info/WHEEL
Lindex-1.1.1.dist-info/top_level.txt
Lindex-1.1.1.dist-info/RECORD
