Metadata-Version: 2.1
Name: Lindex
Version: 1.1.1
Summary: A python Library created to improve functionality of Nested Dictionaries in Python
Author: @some1and2
Author-email: 04x0xx@gmail.com
License: GPL-3.0
License-File: LICENSE
